{
    "/js/app.js": "/js/app.js",
    "/css/app.css": "/css/app.css",
    "/js/app.2c4b3d13bae481f00f08.hot-update.js": "/js/app.2c4b3d13bae481f00f08.hot-update.js",
    "/js/app.fa863bee3b5c90cd2387.hot-update.js": "/js/app.fa863bee3b5c90cd2387.hot-update.js",
    "/js/app.61aad34e744901b557ba.hot-update.js": "/js/app.61aad34e744901b557ba.hot-update.js",
    "/js/app.f0d239088fd99c7b26ae.hot-update.js": "/js/app.f0d239088fd99c7b26ae.hot-update.js",
    "/js/app.a1a29ca4590e98a3b21b.hot-update.js": "/js/app.a1a29ca4590e98a3b21b.hot-update.js",
    "/js/app.94030a028a9152c96e2a.hot-update.js": "/js/app.94030a028a9152c96e2a.hot-update.js",
    "/js/app.7565c31d1ea2e2a46923.hot-update.js": "/js/app.7565c31d1ea2e2a46923.hot-update.js",
    "/js/app.deb917e595e34dabeec8.hot-update.js": "/js/app.deb917e595e34dabeec8.hot-update.js",
    "/js/app.64553525bf936c24af4d.hot-update.js": "/js/app.64553525bf936c24af4d.hot-update.js",
    "/js/app.e0808bac0b263a46607d.hot-update.js": "/js/app.e0808bac0b263a46607d.hot-update.js",
    "/js/app.1c9c536ab6322e4780b1.hot-update.js": "/js/app.1c9c536ab6322e4780b1.hot-update.js",
    "/js/app.63c03394db86b1053b7d.hot-update.js": "/js/app.63c03394db86b1053b7d.hot-update.js",
    "/js/app.32780a26aa4e23ef94f8.hot-update.js": "/js/app.32780a26aa4e23ef94f8.hot-update.js",
    "/js/app.7f1d9b6f1c207b25072f.hot-update.js": "/js/app.7f1d9b6f1c207b25072f.hot-update.js",
    "/js/app.7f29a389641a094a6e0f.hot-update.js": "/js/app.7f29a389641a094a6e0f.hot-update.js"
}
